energymeter2mqtt/__init__.py
energymeter2mqtt/__main__.py
energymeter2mqtt/api.py
energymeter2mqtt/constants.py
energymeter2mqtt/mqtt_handler.py
energymeter2mqtt/mqtt_publish.py
energymeter2mqtt/probe_usb_ports.py
energymeter2mqtt/user_settings.py
energymeter2mqtt/cli_app/__init__.py
energymeter2mqtt/cli_app/energymeter.py
energymeter2mqtt/cli_app/mqtt.py
energymeter2mqtt/cli_app/settings.py
energymeter2mqtt/cli_app/systemd.py
energymeter2mqtt/cli_dev/__init__.py
energymeter2mqtt/cli_dev/code_style.py
energymeter2mqtt/cli_dev/packaging.py
energymeter2mqtt/cli_dev/settings.py
energymeter2mqtt/cli_dev/testing.py
energymeter2mqtt/cli_dev/update_readme_history.py
energymeter2mqtt/definitions/saia_pcd_ald1d5fd.toml
energymeter2mqtt/tests/__init__.py
energymeter2mqtt/tests/test_api.py
energymeter2mqtt/tests/test_definitions.py
energymeter2mqtt/tests/test_doctests.py
energymeter2mqtt/tests/test_project_setup.py
energymeter2mqtt/tests/test_readme.py
energymeter2mqtt/tests/test_readme_history.py
energymeter2mqtt/tests/test_user_settings.py
energymeter2mqtt/tests/test_user_settings_energy_meter_dataclass_1.snapshot.json
energymeter2mqtt/tests/test_user_settings_energy_meter_dataclass_2.snapshot.json
energymeter2mqtt-0.6.3.dist-info/METADATA
energymeter2mqtt-0.6.3.dist-info/WHEEL
energymeter2mqtt-0.6.3.dist-info/entry_points.txt
energymeter2mqtt-0.6.3.dist-info/RECORD
