Metadata-Version: 2.4
Name: energymeter2mqtt
Version: 0.6.3
Summary: Get values from modbus energy meter to MQTT / HomeAssistant
Project-URL: Documentation, https://github.com/jedie/energymeter2mqtt
Project-URL: Source, https://github.com/jedie/energymeter2mqtt
Author-email: Jens Diemer <git@jensdiemer.de>
License: GPL-3.0-or-later
Requires-Python: >=3.11
Requires-Dist: backoff
Requires-Dist: bx-py-utils
Requires-Dist: cli-base-utilities>=0.17.0
Requires-Dist: ha-services>=2.14.0
Requires-Dist: paho-mqtt
Requires-Dist: pymodbus[serial]
Requires-Dist: rich
Requires-Dist: tyro
